fds/__init__.py
fds/sdk/__init__.py
fds/sdk/ExchangeDataFeedSnapshotAPIEntireExchange/__init__.py
fds/sdk/ExchangeDataFeedSnapshotAPIEntireExchange/api_client.py
fds/sdk/ExchangeDataFeedSnapshotAPIEntireExchange/configuration.py
fds/sdk/ExchangeDataFeedSnapshotAPIEntireExchange/exceptions.py
fds/sdk/ExchangeDataFeedSnapshotAPIEntireExchange/model_utils.py
fds/sdk/ExchangeDataFeedSnapshotAPIEntireExchange/rest.py
fds/sdk/ExchangeDataFeedSnapshotAPIEntireExchange/api/__init__.py
fds/sdk/ExchangeDataFeedSnapshotAPIEntireExchange/api/snapshot_api.py
fds/sdk/ExchangeDataFeedSnapshotAPIEntireExchange/apis/__init__.py
fds/sdk/ExchangeDataFeedSnapshotAPIEntireExchange/model/__init__.py
fds/sdk/ExchangeDataFeedSnapshotAPIEntireExchange/model/data.py
fds/sdk/ExchangeDataFeedSnapshotAPIEntireExchange/model/error_messages.py
fds/sdk/ExchangeDataFeedSnapshotAPIEntireExchange/model/inline_response200.py
fds/sdk/ExchangeDataFeedSnapshotAPIEntireExchange/model/meta.py
fds/sdk/ExchangeDataFeedSnapshotAPIEntireExchange/models/__init__.py
fds.sdk.ExchangeDataFeedSnapshotAPIEntireExchange-0.21.14.dist-info/LICENSE
fds.sdk.ExchangeDataFeedSnapshotAPIEntireExchange-0.21.14.dist-info/METADATA
fds.sdk.ExchangeDataFeedSnapshotAPIEntireExchange-0.21.14.dist-info/WHEEL
fds.sdk.ExchangeDataFeedSnapshotAPIEntireExchange-0.21.14.dist-info/top_level.txt
fds.sdk.ExchangeDataFeedSnapshotAPIEntireExchange-0.21.14.dist-info/RECORD
